MANIFEST.in
README.rst
requirements.txt
setup.py
at_common_utils.egg-info/PKG-INFO
at_common_utils.egg-info/SOURCES.txt
at_common_utils.egg-info/dependency_links.txt
at_common_utils.egg-info/requires.txt
at_common_utils.egg-info/top_level.txt
atp/__init__.py
atp/global_data.py
atp/logger.py
atp/requests_utils.py