Metadata-Version: 1.0
Name: at-common-utils
Version: 0.0.4
Summary: UNKNOWN
Home-page: https://pypi.org/project/at-common-utils
Author: at-team
Author-email: hylinux@126.com
License: MIT
Platform: UNKNOWN
